flask_googlestorage/__init__.py
flask_googlestorage/buckets.py
flask_googlestorage/exceptions.py
flask_googlestorage/google_storage.py
flask_googlestorage/utils.py
Flask_GoogleStorage-0.2.0.dist-info/AUTHORS.rst
Flask_GoogleStorage-0.2.0.dist-info/LICENSE
Flask_GoogleStorage-0.2.0.dist-info/METADATA
Flask_GoogleStorage-0.2.0.dist-info/WHEEL
Flask_GoogleStorage-0.2.0.dist-info/top_level.txt
Flask_GoogleStorage-0.2.0.dist-info/RECORD
