Metadata-Version: 2.1
Name: Flask-GoogleStorage
Version: 0.2.0
Summary: Google Cloud Storage for Flask
Home-page: https://github.com/svidela/flask-googlestorage
Author: Santiago Videla
Author-email: santiago.videla@gmail.com
License: MIT
Keywords: flask,google,cloud,storage
Platform: any
Classifier: Intended Audience :: Developers
Classifier: Topic :: Internet :: WWW/HTTP
Classifier: Environment :: Web Environment
Classifier: Framework :: Flask
Classifier: License :: OSI Approved :: MIT License
Classifier: Programming Language :: Python :: 3.8
Classifier: Programming Language :: Python :: 3.9
Classifier: Programming Language :: Python :: 3.10
Classifier: Programming Language :: Python :: 3.11
Requires-Python: >=3.8
License-File: LICENSE
License-File: AUTHORS.rst
Requires-Dist: flask >=1.1.0
Requires-Dist: google-cloud-storage >=2.16
Requires-Dist: tenacity >=8.0.0
